cfog/__init__.py
cfog/metrics/__init__.py
cfog/metrics/levenshtein.cpython-36m-darwin.so
fog/__init__.py
fog/utils.py
fog/cli/__init__.py
fog/cli/__main__.py
fog/cli/cluster.py
fog/cli/split.py
fog/cli/transform.py
fog/cli/utils.py
fog/cli/reporting/__init__.py
fog/cli/reporting/html.py
fog/cli/reporting/toml.py
fog/clustering/__init__.py
fog/clustering/blocking.py
fog/clustering/fagin.py
fog/clustering/intersection_index.py
fog/clustering/key_collision.py
fog/clustering/laesa.py
fog/clustering/minhash.py
fog/clustering/nn_descent.py
fog/clustering/pairwise.py
fog/clustering/passjoin.py
fog/clustering/ppjoin.py
fog/clustering/quickjoin.py
fog/clustering/sorted_neighborhood.py
fog/clustering/utils.py
fog/clustering/vp_tree.py
fog/evaluation/__init__.py
fog/evaluation/best_matching.py
fog/evaluation/utils.py
fog/graph/__init__.py
fog/graph/projection.py
fog/graph/sparsification.py
fog/graph/utils.py
fog/join/__init__.py
fog/join/hashjoin.py
fog/key/__init__.py
fog/key/fingerprint.py
fog/key/levenshtein.py
fog/key/misc.py
fog/key/omission.py
fog/key/skeleton.py
fog/lsh/__init__.py
fog/lsh/minhash.py
fog/lsh/simhash.py
fog/lsh/utils.py
fog/metrics/__init__.py
fog/metrics/cosine.py
fog/metrics/dice.py
fog/metrics/jaccard.py
fog/metrics/overlap.py
fog/metrics/utils.py
fog/phonetics/__init__.py
fog/phonetics/cologne.py
fog/phonetics/rusalka.py
fog/tokenizers/__init__.py
fog/tokenizers/fingerprint.py
fog/tokenizers/ngrams.py
fog/tokenizers/words.py
fog-0.11.8.dist-info/LICENSE.txt
fog-0.11.8.dist-info/METADATA
fog-0.11.8.dist-info/WHEEL
fog-0.11.8.dist-info/entry_points.txt
fog-0.11.8.dist-info/top_level.txt
fog-0.11.8.dist-info/zip-safe
fog-0.11.8.dist-info/RECORD
