Metadata-Version: 2.1
Name: fog
Version: 0.11.8
Summary: A fuzzy matching & clustering library for python.
Home-page: http://github.com/Yomguithereal/fog
Author: Guillaume Plique
Author-email: kropotkinepiotr@gmail.com
License: MIT
Keywords: fuzzy
Platform: UNKNOWN
Requires-Python: >=3
Requires-Dist: dill (>=0.2.7.1)
Requires-Dist: ebbe (<2,>=1.3.1)
Requires-Dist: emoji (<2,>=1)
Requires-Dist: networkx (>=2)
Requires-Dist: phylactery (>=0.1.1)
Requires-Dist: Unidecode (>=1.0.22)
